odoo/addons/mrp_package_propagation/README.rst
odoo/addons/mrp_package_propagation/__init__.py
odoo/addons/mrp_package_propagation/__manifest__.py
odoo/addons/mrp_package_propagation/i18n/es.po
odoo/addons/mrp_package_propagation/i18n/it.po
odoo/addons/mrp_package_propagation/i18n/mrp_package_propagation.pot
odoo/addons/mrp_package_propagation/i18n/pt_BR.po
odoo/addons/mrp_package_propagation/models/__init__.py
odoo/addons/mrp_package_propagation/models/mrp_bom.py
odoo/addons/mrp_package_propagation/models/mrp_bom_line.py
odoo/addons/mrp_package_propagation/models/mrp_production.py
odoo/addons/mrp_package_propagation/models/stock_move.py
odoo/addons/mrp_package_propagation/readme/CONTRIBUTORS.md
odoo/addons/mrp_package_propagation/readme/DESCRIPTION.md
odoo/addons/mrp_package_propagation/readme/USAGE.md
odoo/addons/mrp_package_propagation/static/description/icon.png
odoo/addons/mrp_package_propagation/static/description/index.html
odoo/addons/mrp_package_propagation/tests/__init__.py
odoo/addons/mrp_package_propagation/tests/common.py
odoo/addons/mrp_package_propagation/tests/test_mrp_bom.py
odoo/addons/mrp_package_propagation/tests/test_mrp_production.py
odoo/addons/mrp_package_propagation/views/mrp_bom.xml
odoo/addons/mrp_package_propagation/views/mrp_production.xml
odoo_addon_mrp_package_propagation-18.0.1.0.0.5.dist-info/METADATA
odoo_addon_mrp_package_propagation-18.0.1.0.0.5.dist-info/WHEEL
odoo_addon_mrp_package_propagation-18.0.1.0.0.5.dist-info/top_level.txt
odoo_addon_mrp_package_propagation-18.0.1.0.0.5.dist-info/RECORD
